python_papi-6.0.0.2.dist-info/top_level.txt
python_papi-6.0.0.2.dist-info/RECORD
python_papi-6.0.0.2.dist-info/LICENSE
python_papi-6.0.0.2.dist-info/METADATA
python_papi-6.0.0.2.dist-info/WHEEL
pypapi/events.py
pypapi/papi_low.py
pypapi/consts.py
pypapi/exceptions.py
pypapi/structs.py
pypapi/__init__.py
pypapi/papi_build.py
pypapi/_papi.abi3.so
pypapi/papi_high.py
