Metadata-Version: 2.1
Name: python_papi
Version: 6.0.0.2
Summary: Python binding for the PAPI library
Home-page: https://github.com/flozz/pypapi
Author: Fabien LOISON, Mathilde BOUTIGNY
License: WTFPL
Project-URL: Source Code, https://github.com/flozz/pypapi
Project-URL: Documentation, https://flozz.github.io/pypapi/
Project-URL: Changelog, https://github.com/flozz/pypapi#changelog
Project-URL: Issues, https://github.com/flozz/pypapi/issues
Project-URL: Chat, https://discord.gg/P77sWhuSs4
Project-URL: Donate, https://github.com/flozz/pypapi#support-this-project
Keywords: papi perf performance
License-File: LICENSE
Requires-Dist: cffi >=1.0.0
Provides-Extra: dev
Requires-Dist: nox ; extra == 'dev'
Requires-Dist: flake8 ; extra == 'dev'
Requires-Dist: black ; extra == 'dev'
Requires-Dist: sphinx ; extra == 'dev'
Requires-Dist: sphinx-rtd-theme ; extra == 'dev'
